MANIFEST.in
README.rst
setup.py
image2pyarray/Image2PyArray.py
image2pyarray/__init__.py
image2pyarray.egg-info/PKG-INFO
image2pyarray.egg-info/SOURCES.txt
image2pyarray.egg-info/dependency_links.txt
image2pyarray.egg-info/requires.txt
image2pyarray.egg-info/top_level.txt