Metadata-Version: 1.0
Name: image2pyarray
Version: 0.0.7
Summary: load image easily
Home-page: https://github.com/image2pyarray/image2pyarray
Author: me
Author-email: me@nsa.gov
License: MIT
Platform: UNKNOWN
